crontab_tool/__init__.py
crontab_tool/cli.py
crontab_tool/cron.py
crontab_tool/explain.py
adi_crontab_tool-0.1.2.dist-info/METADATA
adi_crontab_tool-0.1.2.dist-info/WHEEL
adi_crontab_tool-0.1.2.dist-info/entry_points.txt
adi_crontab_tool-0.1.2.dist-info/top_level.txt
adi_crontab_tool-0.1.2.dist-info/RECORD
