Metadata-Version: 2.4
Name: adi-crontab-tool
Version: 0.1.2
Summary: A small CLI to validate and explain cron expressions
Author: Adi
License: MIT
Requires-Python: >=3.13
Provides-Extra: dev
Requires-Dist: pytest; extra == "dev"
